OLD/__init__.py
OLD/anchor_functions.py
OLD/anchor_variables.py
OLD/cmdparse.py
OLD/helpers.py
OLD/main.py
OLD/messages.py
OLD/builtin/__init__.py
OLD/builtin/transformers.py
OLD/builtin/github/__init__.py
OLD/builtin/github/ghcollector.py
OLD/builtin/github/header_transform.py
OLD/core/__init__.py
OLD/core/collector.py
OLD/core/lazyregex.py
OLD/core/parser.py
OLD/core/switches/__init__.py
OLD/core/switches/armedswitch.py
OLD/regex/__init__.py
OLD/regex/markdown/__init__.py
OLD/regex/markdown/patterns.py
OLD/regex/markdown/reobj.py
anchorhub/VERSION
anchorhub/__init__.py
anchorhub/cmdparse.py
anchorhub/collect.py
anchorhub/collector.py
anchorhub/compatibility.py
anchorhub/fileparse.py
anchorhub/main.py
anchorhub/messages.py
anchorhub/writer.py
anchorhub/builtin/__init__.py
anchorhub/builtin/github/__init__.py
anchorhub/builtin/github/collector.py
anchorhub/builtin/github/converter.py
anchorhub/builtin/github/cstrategies.py
anchorhub/builtin/github/switches.py
anchorhub/builtin/github/writer.py
anchorhub/builtin/github/wstrategies.py
anchorhub/builtin/regex/__init__.py
anchorhub/builtin/regex/markdown.py
anchorhub/exceptions/__init__.py
anchorhub/exceptions/validationexception.py
anchorhub/lib/__init__.py
anchorhub/lib/armedcheckswitch.py
anchorhub/lib/armedswitch.py
anchorhub/lib/bunch.py
anchorhub/lib/filetolist.py
anchorhub/lib/lazyregex.py
anchorhub/normalization/__init__.py
anchorhub/normalization/normalize_opts.py
anchorhub/settings/__init__.py
anchorhub/settings/default_settings.py
anchorhub/util/__init__.py
anchorhub/util/addsuffix.py
anchorhub/util/getanchorhubpath.py
anchorhub/util/getfiles.py
anchorhub/util/hasattrs.py
anchorhub/util/stripprefix.py
anchorhub/validation/__init__.py
anchorhub/validation/validate_anchors.py
anchorhub/validation/validate_extensions.py
anchorhub/validation/validate_files.py
anchorhub/validation/validate_input.py
anchorhub/validation/validate_opts.py
anchorhub-0.14.dist-info/DESCRIPTION.rst
anchorhub-0.14.dist-info/METADATA
anchorhub-0.14.dist-info/RECORD
anchorhub-0.14.dist-info/WHEEL
anchorhub-0.14.dist-info/entry_points.txt
anchorhub-0.14.dist-info/metadata.json
anchorhub-0.14.dist-info/top_level.txt
