Metadata-Version: 2.0
Name: anchorhub
Version: 0.14
Summary: Easily utilize GitHub's automatically generated anchors within and across Markdown documents
Home-page: https://github.com/samjabrahams/anchorhub
Author: Sam Abrahams
Author-email: sam@samabrahams.com
License: Apache 2.0
Keywords: markdown anchor links processing
Platform: UNKNOWN
Classifier: Development Status :: 4 - Beta
Classifier: Environment :: Console
Classifier: Intended Audience :: Developers
Classifier: Topic :: Software Development :: Pre-processors
Classifier: License :: OSI Approved :: Apache Software License
Classifier: Operating System :: OS Independent
Classifier: Programming Language :: Python
Classifier: Programming Language :: Python :: 2.7
Classifier: Programming Language :: Python :: 3.3
Classifier: Programming Language :: Python :: 3.4
Classifier: Programming Language :: Python :: 3.5
Requires-Dist: nose
